proserve/__init__.py
proserve/__main__.py
proserve/cli.py
proserve/runner.py
proserve/cli/__init__.py
proserve/cli/__main__.py
proserve/cli/commands.py
proserve/cli/generators.py
proserve/cli/helpers.py
proserve/cli/main_cli.py
proserve/cli/parsers.py
proserve/core/__init__.py
proserve/core/autotest.py
proserve/core/endpoint_manager.py
proserve/core/grpc_handler.py
proserve/core/logging.py
proserve/core/manifest.py
proserve/core/mock_system.py
proserve/core/service.py
proserve/core/service_builder.py
proserve/core/service_core.py
proserve/core/service_fallback.py
proserve/core/service_refactored.py
proserve/core/shell.py
proserve/core/static_handler.py
proserve/core/static_server.py
proserve/core/task_manager.py
proserve/core/logging_system/__init__.py
proserve/core/logging_system/broadcaster.py
proserve/core/logging_system/config.py
proserve/core/logging_system/file_handler.py
proserve/core/logging_system/setup.py
proserve/core/logging_system/utilities.py
proserve/core/mocking/__init__.py
proserve/core/mocking/mock_handler.py
proserve/core/mocking/mock_manager.py
proserve/core/mocking/mock_types.py
proserve/core/static/__init__.py
proserve/core/static/api_proxy.py
proserve/core/static/cache_manager.py
proserve/core/static/cdn_manager.py
proserve/core/static/website_server.py
proserve/discovery/__init__.py
proserve/discovery/detector.py
proserve/discovery/generator.py
proserve/discovery/scanner.py
proserve/discovery/detection/__init__.py
proserve/discovery/detection/core_detection.py
proserve/discovery/detection/database_detection.py
proserve/discovery/detection/deployment_detection.py
proserve/discovery/detection/endpoint_detectors.py
proserve/discovery/detection/framework_detector.py
proserve/discovery/detection/framework_patterns.py
proserve/discovery/detection/framework_utilities.py
proserve/discovery/detection/service_detector.py
proserve/discovery/detection/service_models.py
proserve/migration/__init__.py
proserve/migration/config.py
proserve-2.0.6.dist-info/licenses/LICENSE
proserve-2.0.6.dist-info/METADATA
proserve-2.0.6.dist-info/WHEEL
proserve-2.0.6.dist-info/entry_points.txt
proserve-2.0.6.dist-info/top_level.txt
proserve-2.0.6.dist-info/RECORD
